<?xml version="1.0" encoding="UTF-8"?>
<!DOCTYPE mapper PUBLIC "-//mybatis.org//DTD Mapper 3.0//EN" "http://mybatis.org/dtd/mybatis-3-mapper.dtd">
<mapper namespace="com.pipimovie.dao.CotypeDOMapper">
  <resultMap id="BaseResultMap" type="com.pipimovie.dataobject.CotypeDO">
    <!--
      WARNING - @mbg.generated
      This element is automatically generated by MyBatis Generator, do not modify.
      This element was generated on Wed Jun 24 11:20:32 CST 2020.
    -->
    <constructor>
      <idArg column="tid" javaType="java.lang.Integer" jdbcType="INTEGER" />
      <arg column="cid" javaType="java.lang.Short" jdbcType="SMALLINT" />
      <arg column="tname" javaType="java.lang.String" jdbcType="VARCHAR" />
      <arg column="siteurl" javaType="java.lang.String" jdbcType="CHAR" />
      <arg column="getherday" javaType="java.lang.Short" jdbcType="SMALLINT" />
      <arg column="playfrom" javaType="java.lang.String" jdbcType="VARCHAR" />
      <arg column="autocls" javaType="java.lang.String" jdbcType="CHAR" />
      <arg column="classid" javaType="java.lang.Short" jdbcType="SMALLINT" />
      <arg column="coding" javaType="java.lang.String" jdbcType="VARCHAR" />
      <arg column="sock" javaType="java.lang.String" jdbcType="CHAR" />
      <arg column="addtime" javaType="java.lang.Integer" jdbcType="INTEGER" />
      <arg column="cjtime" javaType="java.lang.Integer" jdbcType="INTEGER" />
      <arg column="listconfig" javaType="java.lang.String" jdbcType="VARCHAR" />
      <arg column="itemconfig" javaType="java.lang.String" jdbcType="VARCHAR" />
      <arg column="isok" javaType="java.lang.Boolean" jdbcType="BIT" />
      <arg column="cotype" javaType="java.lang.Byte" jdbcType="TINYINT" />
    </constructor>
  </resultMap>
  <sql id="Base_Column_List">
    <!--
      WARNING - @mbg.generated
      This element is automatically generated by MyBatis Generator, do not modify.
      This element was generated on Wed Jun 24 11:20:32 CST 2020.
    -->
    tid, cid, tname, siteurl, getherday, playfrom, autocls, classid, coding, sock, addtime, 
    cjtime, listconfig, itemconfig, isok, cotype
  </sql>
  <select id="selectByPrimaryKey" parameterType="java.lang.Integer" resultMap="BaseResultMap">
    <!--
      WARNING - @mbg.generated
      This element is automatically generated by MyBatis Generator, do not modify.
      This element was generated on Wed Jun 24 11:20:32 CST 2020.
    -->
    select 
    <include refid="Base_Column_List" />
    from sea_co_type
    where tid = #{tid,jdbcType=INTEGER}
  </select>
  <delete id="deleteByPrimaryKey" parameterType="java.lang.Integer">
    <!--
      WARNING - @mbg.generated
      This element is automatically generated by MyBatis Generator, do not modify.
      This element was generated on Wed Jun 24 11:20:32 CST 2020.
    -->
    delete from sea_co_type
    where tid = #{tid,jdbcType=INTEGER}
  </delete>
  <insert id="insert" parameterType="com.pipimovie.dataobject.CotypeDO">
    <!--
      WARNING - @mbg.generated
      This element is automatically generated by MyBatis Generator, do not modify.
      This element was generated on Wed Jun 24 11:20:32 CST 2020.
    -->
    insert into sea_co_type (tid, cid, tname, 
      siteurl, getherday, playfrom, 
      autocls, classid, coding, 
      sock, addtime, cjtime, 
      listconfig, itemconfig, isok, 
      cotype)
    values (#{tid,jdbcType=INTEGER}, #{cid,jdbcType=SMALLINT}, #{tname,jdbcType=VARCHAR}, 
      #{siteurl,jdbcType=CHAR}, #{getherday,jdbcType=SMALLINT}, #{playfrom,jdbcType=VARCHAR}, 
      #{autocls,jdbcType=CHAR}, #{classid,jdbcType=SMALLINT}, #{coding,jdbcType=VARCHAR}, 
      #{sock,jdbcType=CHAR}, #{addtime,jdbcType=INTEGER}, #{cjtime,jdbcType=INTEGER}, 
      #{listconfig,jdbcType=VARCHAR}, #{itemconfig,jdbcType=VARCHAR}, #{isok,jdbcType=BIT}, 
      #{cotype,jdbcType=TINYINT})
  </insert>
  <insert id="insertSelective" parameterType="com.pipimovie.dataobject.CotypeDO">
    <!--
      WARNING - @mbg.generated
      This element is automatically generated by MyBatis Generator, do not modify.
      This element was generated on Wed Jun 24 11:20:32 CST 2020.
    -->
    insert into sea_co_type
    <trim prefix="(" suffix=")" suffixOverrides=",">
      <if test="tid != null">
        tid,
      </if>
      <if test="cid != null">
        cid,
      </if>
      <if test="tname != null">
        tname,
      </if>
      <if test="siteurl != null">
        siteurl,
      </if>
      <if test="getherday != null">
        getherday,
      </if>
      <if test="playfrom != null">
        playfrom,
      </if>
      <if test="autocls != null">
        autocls,
      </if>
      <if test="classid != null">
        classid,
      </if>
      <if test="coding != null">
        coding,
      </if>
      <if test="sock != null">
        sock,
      </if>
      <if test="addtime != null">
        addtime,
      </if>
      <if test="cjtime != null">
        cjtime,
      </if>
      <if test="listconfig != null">
        listconfig,
      </if>
      <if test="itemconfig != null">
        itemconfig,
      </if>
      <if test="isok != null">
        isok,
      </if>
      <if test="cotype != null">
        cotype,
      </if>
    </trim>
    <trim prefix="values (" suffix=")" suffixOverrides=",">
      <if test="tid != null">
        #{tid,jdbcType=INTEGER},
      </if>
      <if test="cid != null">
        #{cid,jdbcType=SMALLINT},
      </if>
      <if test="tname != null">
        #{tname,jdbcType=VARCHAR},
      </if>
      <if test="siteurl != null">
        #{siteurl,jdbcType=CHAR},
      </if>
      <if test="getherday != null">
        #{getherday,jdbcType=SMALLINT},
      </if>
      <if test="playfrom != null">
        #{playfrom,jdbcType=VARCHAR},
      </if>
      <if test="autocls != null">
        #{autocls,jdbcType=CHAR},
      </if>
      <if test="classid != null">
        #{classid,jdbcType=SMALLINT},
      </if>
      <if test="coding != null">
        #{coding,jdbcType=VARCHAR},
      </if>
      <if test="sock != null">
        #{sock,jdbcType=CHAR},
      </if>
      <if test="addtime != null">
        #{addtime,jdbcType=INTEGER},
      </if>
      <if test="cjtime != null">
        #{cjtime,jdbcType=INTEGER},
      </if>
      <if test="listconfig != null">
        #{listconfig,jdbcType=VARCHAR},
      </if>
      <if test="itemconfig != null">
        #{itemconfig,jdbcType=VARCHAR},
      </if>
      <if test="isok != null">
        #{isok,jdbcType=BIT},
      </if>
      <if test="cotype != null">
        #{cotype,jdbcType=TINYINT},
      </if>
    </trim>
  </insert>
  <update id="updateByPrimaryKeySelective" parameterType="com.pipimovie.dataobject.CotypeDO">
    <!--
      WARNING - @mbg.generated
      This element is automatically generated by MyBatis Generator, do not modify.
      This element was generated on Wed Jun 24 11:20:32 CST 2020.
    -->
    update sea_co_type
    <set>
      <if test="cid != null">
        cid = #{cid,jdbcType=SMALLINT},
      </if>
      <if test="tname != null">
        tname = #{tname,jdbcType=VARCHAR},
      </if>
      <if test="siteurl != null">
        siteurl = #{siteurl,jdbcType=CHAR},
      </if>
      <if test="getherday != null">
        getherday = #{getherday,jdbcType=SMALLINT},
      </if>
      <if test="playfrom != null">
        playfrom = #{playfrom,jdbcType=VARCHAR},
      </if>
      <if test="autocls != null">
        autocls = #{autocls,jdbcType=CHAR},
      </if>
      <if test="classid != null">
        classid = #{classid,jdbcType=SMALLINT},
      </if>
      <if test="coding != null">
        coding = #{coding,jdbcType=VARCHAR},
      </if>
      <if test="sock != null">
        sock = #{sock,jdbcType=CHAR},
      </if>
      <if test="addtime != null">
        addtime = #{addtime,jdbcType=INTEGER},
      </if>
      <if test="cjtime != null">
        cjtime = #{cjtime,jdbcType=INTEGER},
      </if>
      <if test="listconfig != null">
        listconfig = #{listconfig,jdbcType=VARCHAR},
      </if>
      <if test="itemconfig != null">
        itemconfig = #{itemconfig,jdbcType=VARCHAR},
      </if>
      <if test="isok != null">
        isok = #{isok,jdbcType=BIT},
      </if>
      <if test="cotype != null">
        cotype = #{cotype,jdbcType=TINYINT},
      </if>
    </set>
    where tid = #{tid,jdbcType=INTEGER}
  </update>
  <update id="updateByPrimaryKey" parameterType="com.pipimovie.dataobject.CotypeDO">
    <!--
      WARNING - @mbg.generated
      This element is automatically generated by MyBatis Generator, do not modify.
      This element was generated on Wed Jun 24 11:20:32 CST 2020.
    -->
    update sea_co_type
    set cid = #{cid,jdbcType=SMALLINT},
      tname = #{tname,jdbcType=VARCHAR},
      siteurl = #{siteurl,jdbcType=CHAR},
      getherday = #{getherday,jdbcType=SMALLINT},
      playfrom = #{playfrom,jdbcType=VARCHAR},
      autocls = #{autocls,jdbcType=CHAR},
      classid = #{classid,jdbcType=SMALLINT},
      coding = #{coding,jdbcType=VARCHAR},
      sock = #{sock,jdbcType=CHAR},
      addtime = #{addtime,jdbcType=INTEGER},
      cjtime = #{cjtime,jdbcType=INTEGER},
      listconfig = #{listconfig,jdbcType=VARCHAR},
      itemconfig = #{itemconfig,jdbcType=VARCHAR},
      isok = #{isok,jdbcType=BIT},
      cotype = #{cotype,jdbcType=TINYINT}
    where tid = #{tid,jdbcType=INTEGER}
  </update>
</mapper>