<?xml version="1.0" encoding="UTF-8"?>
<!DOCTYPE mapper PUBLIC "-//mybatis.org//DTD Mapper 3.0//EN" "http://mybatis.org/dtd/mybatis-3-mapper.dtd">
<mapper namespace="com.pipimovie.dao.TypeDOMapper">
  <resultMap id="BaseResultMap" type="com.pipimovie.dataobject.TypeDO">
    <!--
      WARNING - @mbg.generated
      This element is automatically generated by MyBatis Generator, do not modify.
      This element was generated on Wed Jun 24 11:20:32 CST 2020.
    -->
    <constructor>
      <idArg column="tid" javaType="java.lang.Short" jdbcType="SMALLINT" />
      <arg column="upid" javaType="java.lang.Byte" jdbcType="TINYINT" />
      <arg column="tname" javaType="java.lang.String" jdbcType="CHAR" />
      <arg column="tenname" javaType="java.lang.String" jdbcType="CHAR" />
      <arg column="torder" javaType="java.lang.Integer" jdbcType="INTEGER" />
      <arg column="templist" javaType="java.lang.String" jdbcType="CHAR" />
      <arg column="templist_1" javaType="java.lang.String" jdbcType="CHAR" />
      <arg column="templist_2" javaType="java.lang.String" jdbcType="CHAR" />
      <arg column="title" javaType="java.lang.String" jdbcType="CHAR" />
      <arg column="keyword" javaType="java.lang.String" jdbcType="CHAR" />
      <arg column="description" javaType="java.lang.String" jdbcType="CHAR" />
      <arg column="ishidden" javaType="java.lang.Short" jdbcType="SMALLINT" />
      <arg column="unionid" javaType="java.lang.String" jdbcType="VARCHAR" />
      <arg column="tptype" javaType="java.lang.Short" jdbcType="SMALLINT" />
    </constructor>
  </resultMap>
  <sql id="Base_Column_List">
    <!--
      WARNING - @mbg.generated
      This element is automatically generated by MyBatis Generator, do not modify.
      This element was generated on Wed Jun 24 11:20:32 CST 2020.
    -->
    tid, upid, tname, tenname, torder, templist, templist_1, templist_2, title, keyword, 
    description, ishidden, unionid, tptype
  </sql>
  <select id="selectByPrimaryKey" parameterType="java.lang.Short" resultMap="BaseResultMap">
    <!--
      WARNING - @mbg.generated
      This element is automatically generated by MyBatis Generator, do not modify.
      This element was generated on Wed Jun 24 11:20:32 CST 2020.
    -->
    select 
    <include refid="Base_Column_List" />
    from sea_type
    where tid = #{tid,jdbcType=SMALLINT}
  </select>
  <delete id="deleteByPrimaryKey" parameterType="java.lang.Short">
    <!--
      WARNING - @mbg.generated
      This element is automatically generated by MyBatis Generator, do not modify.
      This element was generated on Wed Jun 24 11:20:32 CST 2020.
    -->
    delete from sea_type
    where tid = #{tid,jdbcType=SMALLINT}
  </delete>
  <insert id="insert" parameterType="com.pipimovie.dataobject.TypeDO">
    <!--
      WARNING - @mbg.generated
      This element is automatically generated by MyBatis Generator, do not modify.
      This element was generated on Wed Jun 24 11:20:32 CST 2020.
    -->
    insert into sea_type (tid, upid, tname, 
      tenname, torder, templist, 
      templist_1, templist_2, title, 
      keyword, description, ishidden, 
      unionid, tptype)
    values (#{tid,jdbcType=SMALLINT}, #{upid,jdbcType=TINYINT}, #{tname,jdbcType=CHAR}, 
      #{tenname,jdbcType=CHAR}, #{torder,jdbcType=INTEGER}, #{templist,jdbcType=CHAR}, 
      #{templist1,jdbcType=CHAR}, #{templist2,jdbcType=CHAR}, #{title,jdbcType=CHAR}, 
      #{keyword,jdbcType=CHAR}, #{description,jdbcType=CHAR}, #{ishidden,jdbcType=SMALLINT}, 
      #{unionid,jdbcType=VARCHAR}, #{tptype,jdbcType=SMALLINT})
  </insert>
  <insert id="insertSelective" parameterType="com.pipimovie.dataobject.TypeDO">
    <!--
      WARNING - @mbg.generated
      This element is automatically generated by MyBatis Generator, do not modify.
      This element was generated on Wed Jun 24 11:20:32 CST 2020.
    -->
    insert into sea_type
    <trim prefix="(" suffix=")" suffixOverrides=",">
      <if test="tid != null">
        tid,
      </if>
      <if test="upid != null">
        upid,
      </if>
      <if test="tname != null">
        tname,
      </if>
      <if test="tenname != null">
        tenname,
      </if>
      <if test="torder != null">
        torder,
      </if>
      <if test="templist != null">
        templist,
      </if>
      <if test="templist1 != null">
        templist_1,
      </if>
      <if test="templist2 != null">
        templist_2,
      </if>
      <if test="title != null">
        title,
      </if>
      <if test="keyword != null">
        keyword,
      </if>
      <if test="description != null">
        description,
      </if>
      <if test="ishidden != null">
        ishidden,
      </if>
      <if test="unionid != null">
        unionid,
      </if>
      <if test="tptype != null">
        tptype,
      </if>
    </trim>
    <trim prefix="values (" suffix=")" suffixOverrides=",">
      <if test="tid != null">
        #{tid,jdbcType=SMALLINT},
      </if>
      <if test="upid != null">
        #{upid,jdbcType=TINYINT},
      </if>
      <if test="tname != null">
        #{tname,jdbcType=CHAR},
      </if>
      <if test="tenname != null">
        #{tenname,jdbcType=CHAR},
      </if>
      <if test="torder != null">
        #{torder,jdbcType=INTEGER},
      </if>
      <if test="templist != null">
        #{templist,jdbcType=CHAR},
      </if>
      <if test="templist1 != null">
        #{templist1,jdbcType=CHAR},
      </if>
      <if test="templist2 != null">
        #{templist2,jdbcType=CHAR},
      </if>
      <if test="title != null">
        #{title,jdbcType=CHAR},
      </if>
      <if test="keyword != null">
        #{keyword,jdbcType=CHAR},
      </if>
      <if test="description != null">
        #{description,jdbcType=CHAR},
      </if>
      <if test="ishidden != null">
        #{ishidden,jdbcType=SMALLINT},
      </if>
      <if test="unionid != null">
        #{unionid,jdbcType=VARCHAR},
      </if>
      <if test="tptype != null">
        #{tptype,jdbcType=SMALLINT},
      </if>
    </trim>
  </insert>
  <update id="updateByPrimaryKeySelective" parameterType="com.pipimovie.dataobject.TypeDO">
    <!--
      WARNING - @mbg.generated
      This element is automatically generated by MyBatis Generator, do not modify.
      This element was generated on Wed Jun 24 11:20:32 CST 2020.
    -->
    update sea_type
    <set>
      <if test="upid != null">
        upid = #{upid,jdbcType=TINYINT},
      </if>
      <if test="tname != null">
        tname = #{tname,jdbcType=CHAR},
      </if>
      <if test="tenname != null">
        tenname = #{tenname,jdbcType=CHAR},
      </if>
      <if test="torder != null">
        torder = #{torder,jdbcType=INTEGER},
      </if>
      <if test="templist != null">
        templist = #{templist,jdbcType=CHAR},
      </if>
      <if test="templist1 != null">
        templist_1 = #{templist1,jdbcType=CHAR},
      </if>
      <if test="templist2 != null">
        templist_2 = #{templist2,jdbcType=CHAR},
      </if>
      <if test="title != null">
        title = #{title,jdbcType=CHAR},
      </if>
      <if test="keyword != null">
        keyword = #{keyword,jdbcType=CHAR},
      </if>
      <if test="description != null">
        description = #{description,jdbcType=CHAR},
      </if>
      <if test="ishidden != null">
        ishidden = #{ishidden,jdbcType=SMALLINT},
      </if>
      <if test="unionid != null">
        unionid = #{unionid,jdbcType=VARCHAR},
      </if>
      <if test="tptype != null">
        tptype = #{tptype,jdbcType=SMALLINT},
      </if>
    </set>
    where tid = #{tid,jdbcType=SMALLINT}
  </update>
  <update id="updateByPrimaryKey" parameterType="com.pipimovie.dataobject.TypeDO">
    <!--
      WARNING - @mbg.generated
      This element is automatically generated by MyBatis Generator, do not modify.
      This element was generated on Wed Jun 24 11:20:32 CST 2020.
    -->
    update sea_type
    set upid = #{upid,jdbcType=TINYINT},
      tname = #{tname,jdbcType=CHAR},
      tenname = #{tenname,jdbcType=CHAR},
      torder = #{torder,jdbcType=INTEGER},
      templist = #{templist,jdbcType=CHAR},
      templist_1 = #{templist1,jdbcType=CHAR},
      templist_2 = #{templist2,jdbcType=CHAR},
      title = #{title,jdbcType=CHAR},
      keyword = #{keyword,jdbcType=CHAR},
      description = #{description,jdbcType=CHAR},
      ishidden = #{ishidden,jdbcType=SMALLINT},
      unionid = #{unionid,jdbcType=VARCHAR},
      tptype = #{tptype,jdbcType=SMALLINT}
    where tid = #{tid,jdbcType=SMALLINT}
  </update>
  <select id="listAll" parameterType="java.lang.Short" resultMap="BaseResultMap">
    <!--
      WARNING - @mbg.generated
      This element is automatically generated by MyBatis Generator, do not modify.
      This element was generated on Wed Jun 24 11:20:32 CST 2020.
    -->
    select
    <include refid="Base_Column_List" />
    from sea_type
  </select>

  <select id="listByPid" parameterType="java.lang.Byte" resultMap="BaseResultMap">
    <!--
      WARNING - @mbg.generated
      This element is automatically generated by MyBatis Generator, do not modify.
      This element was generated on Wed Jun 24 11:20:32 CST 2020.
    -->
    select
    <include refid="Base_Column_List" />
    from sea_type
    where upid = #{pid,jdbcType=TINYINT}
  </select>
</mapper>